criminalip/__init__.py
criminalip/client.py
criminalip/constants.py
criminalip/util.py
criminalip-0.0.1.dist-info/LICENSE
criminalip-0.0.1.dist-info/METADATA
criminalip-0.0.1.dist-info/WHEEL
criminalip-0.0.1.dist-info/top_level.txt
criminalip-0.0.1.dist-info/RECORD
